calculadora_python/__init__.py
calculadora_python/menu_operacoes.py
calculadora_python/operacoes.py
calculadora_python-0.0.1.dist-info/METADATA
calculadora_python-0.0.1.dist-info/WHEEL
calculadora_python-0.0.1.dist-info/top_level.txt
calculadora_python-0.0.1.dist-info/RECORD
