Metadata-Version: 2.4
Name: calculadora-python
Version: 0.0.1
Summary: Uma calculadora simples feita com python
Home-page: https://github.com/JuanDaMata/simple-package-template
Author: Juan da Mata
Author-email: juandamata2000@hotmail.com
License: MIT
Requires-Python: >=3.8
Dynamic: author
Dynamic: author-email
Dynamic: description
Dynamic: description-content-type
Dynamic: home-page
Dynamic: license
Dynamic: requires-python
Dynamic: summary
